core/__init__.py
core/scheduler.py
core/scheduler_v0.py
core/common/__init__.py
core/primitives/__init__.py
core/primitives/ingestion/__init__.py
core/primitives/transformation/__init__.py
core/runtime/__init__.py
eyvitel_lambda_sdk-0.3.dist-info/METADATA
eyvitel_lambda_sdk-0.3.dist-info/WHEEL
eyvitel_lambda_sdk-0.3.dist-info/top_level.txt
eyvitel_lambda_sdk-0.3.dist-info/RECORD
