Metadata-Version: 2.1
Name: eyvitel-lambda-sdk
Version: 0.3
Summary: Lambda Workflow AI
Author: Shankar Narayan G
License: MIT
Requires-Dist: requests
